odoo/addons/product_mrp_info/README.rst
odoo/addons/product_mrp_info/__init__.py
odoo/addons/product_mrp_info/__manifest__.py
odoo/addons/product_mrp_info/i18n/fr.po
odoo/addons/product_mrp_info/i18n/product_mrp_info.pot
odoo/addons/product_mrp_info/i18n/pt_BR.po
odoo/addons/product_mrp_info/models/__init__.py
odoo/addons/product_mrp_info/models/product.py
odoo/addons/product_mrp_info/readme/CONTRIBUTORS.rst
odoo/addons/product_mrp_info/readme/DESCRIPTION.rst
odoo/addons/product_mrp_info/readme/USAGE.rst
odoo/addons/product_mrp_info/static/description/icon.png
odoo/addons/product_mrp_info/static/description/index.html
odoo/addons/product_mrp_info/tests/__init__.py
odoo/addons/product_mrp_info/tests/test_product_mrp_info.py
odoo/addons/product_mrp_info/views/product_views.xml
odoo12_addon_product_mrp_info-12.0.1.0.1.dist-info/METADATA
odoo12_addon_product_mrp_info-12.0.1.0.1.dist-info/WHEEL
odoo12_addon_product_mrp_info-12.0.1.0.1.dist-info/top_level.txt
odoo12_addon_product_mrp_info-12.0.1.0.1.dist-info/RECORD
